{
    "ReachMaster": {
        "data_dir": "/home/pns/ReachMaster/software/reach_master",
        "config_file": "Default",
        "exp_control_port": "/dev/ttyACM0",
        "rob_control_port": "/dev/ttyACM2",
        "serial_baud": 2000000,
        "control_timeout": 5
    },
    "CameraSettings": {
        "num_cams": 3,
        "imgdataformat": "XI_RAW8",
        "fps": 200,
        "exposure": 2000,
        "gain": 15.0,
        "sensor_feature_value": 1,
        "gpi_selector": "XI_GPI_PORT1",
        "gpi_mode": "XI_GPI_TRIGGER",
        "trigger_source": "XI_TRG_EDGE_RISING",
        "gpo_selector": "XI_GPO_PORT1",
        "gpo_mode": "XI_GPO_EXPOSURE_ACTIVE",
        "img_width": 688,
        "img_height": 688,
        "offset_x": 304,
        "offset_y": 168,
        "downsampling": "XI_DWN_1x1",
        "saved_pois": [],
        "poi_threshold": 15.0
    },
    "ExperimentSettings": {
        "baseline_dur": 5.0,
        "reach_timeout": 4000,
        "flush_dur": 10000,
        "solenoid_open_dur": 75,
        "solenoid_bounce_dur": 500,
        "reward_win_dur": 3000,
        "max_rewards": 3,
        "lights_off_dur": 3000,
        "lights_on_dur": 5000,
        "reach_delay": 100
    },
    "RobotSettings": {
        "calibration_file": null,
        "dis": null,
        "pos": null,
        "x_push_dur": null,
        "x_pull_dur": null,
        "y_push_dur": null,
        "y_pull_dur": null,
        "z_push_dur": null,
        "z_pull_dur": null,
        "command_type": null,
        "command_set": null,
        "command_file": null,
        "x_command_pos": null,
        "y_command_pos": null,
        "z_command_pos": null,
        "r_command_pos": null,
        "theta_y_command_pos": null,
        "theta_z_command_pos": null,
        "reach_dist_min": 10,
        "reach_dist_max": 40,
        "reach_angle_max": 1.0471975511965976,
        "ygimbal_to_joint": 64,
        "zgimbal_to_joint": 47,
        "xgimbal_xoffset": 168,
        "ygimbal_yoffset": 100,
        "zgimbal_zoffset": 117,
        "x_origin": 1024,
        "y_origin": 608,
        "z_origin": 531,
        "pos_smoothing": 0.1,
        "tol": 6.8,
        "period": 125000.0,
        "off_dur": 1000,
        "num_tol": 5,
        "x_push_wt": 1.0,
        "x_pull_wt": 1.0,
        "y_push_wt": 1.0,
        "y_pull_wt": 1.0,
        "z_push_wt": 1.0,
        "z_pull_wt": 1.0,
        "rew_zone_x": 1000,
        "rew_zone_y_min": 558,
        "rew_zone_y_max": 658,
        "rew_zone_z_min": 481,
        "rew_zone_z_max": 581
    },
    "Protocol": {
        "type": "TRIALS"
    }
}